ptgscroller/__init__.py
ptgscroller/__main__.py
ptgscroller/scroller.py
ptgscroller/scrollmake.py
ptgscroller/widgets.py
ptgscroller/xml_handler.py
ptgscroller-0.1.0.dist-info/LICENSE
ptgscroller-0.1.0.dist-info/METADATA
ptgscroller-0.1.0.dist-info/WHEEL
ptgscroller-0.1.0.dist-info/RECORD
