Metadata-Version: 2.1
Name: ptgscroller
Version: 0.1.0
Summary: PTG Scroller reads scroll files with the .scrl extension and displays the contents in a PyTermGUI session
Author: Sean Del Castillo
Author-email: seanbdcastillo@gmail.com
Requires-Python: >=3.10,<4.0
Classifier: Programming Language :: Python :: 3
Classifier: Programming Language :: Python :: 3.10
Classifier: Programming Language :: Python :: 3.11
Requires-Dist: pillow (>=9.5.0,<10.0.0)
Requires-Dist: pytermgui (>=7.4.0,<8.0.0)
